DMC/__init__.py
DMC/exodmc.py
ExoDMC-1.1b0.dist-info/LICENSE
ExoDMC-1.1b0.dist-info/METADATA
ExoDMC-1.1b0.dist-info/WHEEL
ExoDMC-1.1b0.dist-info/top_level.txt
ExoDMC-1.1b0.dist-info/RECORD
