Metadata-Version: 2.1
Name: ExoDMC
Version: 1.1b0
Summary: Exoplanet Detection Map Calculator
Home-page: https://github.com/mbonav/Exo_DMC
Author: Mariangela Bonavita
Author-email: mbonav@roe.ac.uk
License: UNKNOWN
Platform: UNKNOWN
Classifier: Programming Language :: Python :: 3
Classifier: License :: OSI Approved :: MIT License
Classifier: Operating System :: OS Independent
Requires-Python: >=3.6
